saylaniCalc/init.py
saylaniCalc-0.1.dist-info/METADATA
saylaniCalc-0.1.dist-info/WHEEL
saylaniCalc-0.1.dist-info/top_level.txt
saylaniCalc-0.1.dist-info/RECORD
