Metadata-Version: 2.1
Name: saylaniCalc
Version: 0.1
Summary: this is a package
Author: Sir Qasim and Syed Muhammad Mooazam
License: UNKNOWN
Platform: UNKNOWN
